{
  "source": "fallback",
  "requirements": {
    "minimum": {
      "cpu": "AMD Ryzen 3 1200 / Intel Core i5-4460",
      "gpu": "AMD Radeon RX 460 4GB / NVIDIA GeForce GTX 960 4GB",
      "ram": "8 GB",
      "ramGB": 8,
      "storage": "60 GB",
      "storageGB": 60,
      "os": "Windows 10 64-bit"
    },
    "recommended": {
      "cpu": "AMD Ryzen 3 1200 / Intel Core i5-4460",
      "gpu": "AMD Radeon RX 460 4GB / NVIDIA GeForce GTX 960 4GB",
      "ram": "8 GB",
      "ramGB": 8,
      "storage": "60 GB",
      "storageGB": 60,
      "os": "Windows 10 64-bit"
    }
  },
  "fetchedAt": "2026-04-21T17:01:12.274Z"
}